[
  {
    "id": 3,
    "email": "amr@gmail.com",
    "name": "amr",
    "password": "P@ssw0rd",
    "gender": "M",
    "birthdate": "2023-11-26",
    "posts": [
      {
        "id": 1,
        "userId": 3,
        "content": "dajdfalfjf",
        "comments": [],
        "taggedUsers": [],
        "likers": []
      },
      {
        "id": 2,
        "userId": 3,
        "content": "sdsaddad",
        "privacy": "PUBLIC",
        "comments": [],
        "taggedUsers": [],
        "likers": []
      }
    ],
    "friends": []
  },
  {
    "id": 1,
    "email": "eren@gmail.com",
    "name": "eren",
    "password": "P@ssw0rd",
    "gender": "M",
    "birthdate": "2023-11-26",
    "posts": [
      {
        "id": 1,
        "userId": 1,
        "content": "TATAKAI!!!!!!",
        "comments": [],
        "taggedUsers": [],
        "likers": []
      },
      {
        "id": 2,
        "userId": 1,
        "content": "I love Mikasa but the world is cruel :(",
        "comments": [],
        "taggedUsers": [],
        "likers": []
      },
      {
        "id": 3,
        "userId": 1,
        "content": "Okasan!!!!!",
        "comments": [],
        "taggedUsers": [],
        "likers": []
      }
    ],
    "friends": []
  },
  {
    "id": 4,
    "email": "jose@gmail.com",
    "name": "jose ",
    "password": "Joe26dec@",
    "gender": "M",
    "birthdate": "2023-11-29",
    "posts": [
      {
        "id": 1,
        "userId": 4,
        "content": "a7a neeek",
        "comments": [],
        "taggedUsers": [],
        "likers": []
      }
    ],
    "friends": []
  },
  {
    "id": 2,
    "email": "jojo@gmail.com",
    "name": "jojo",
    "password": "S#33rrff",
    "gender": "M",
    "birthdate": "2023-11-26",
    "posts": [
      {
        "id": 1,
        "userId": 2,
        "content": "ssdfdf",
        "comments": [],
        "taggedUsers": [],
        "likers": []
      }
    ],
    "friends": []
  }
]